{"C:\\Users\\lauta\\Desktop\\Luciana\\Lu\\Prep-Course\\03-JS-II\\homework\\tests\\JSII.test.js":{"passing":10,"tries":1},"C:\\Users\\PC BUSTO\\Documents\\GitHub\\Prep-Course\\03-JS-II\\homework\\tests\\JSII.test.js":{"passing":0,"tries":8},"C:\\Users\\PC BUSTO\\Documents\\GitHub\\Prep-Course\\02-JS-I\\homework\\tests\\JSI.test.js":{"passing":35,"tries":2},"C:\\Users\\PC BUSTO\\Documents\\GitHub\\Prep-Course\\04-JS-III\\homework\\tests\\JSIII.test.js":{"passing":0,"tries":2},"C:\\Users\\PC BUSTO\\Documents\\GitHub\\Prep-Course\\05-JS-IV\\homework\\tests\\JSIV.test.js":{"passing":0,"tries":2},"C:\\Users\\PC BUSTO\\Documents\\GitHub\\Prep-Course\\10-JS-Extra-Homeworks\\homework\\tests\\JSX.test.js":{"passing":0,"tries":2},"C:\\Users\\PC BUSTO\\Documents\\GitHub\\Prep-Course\\07-JS-VI\\homework\\tests\\JSVI.test.js":{"passing":0,"tries":2},"C:\\Users\\PC BUSTO\\Documents\\GitHub\\Prep-Course\\06-JS-V\\homework\\tests\\JSV.test.js":{"passing":0,"tries":2}}